<?xml version="1.0" encoding="utf-8"?>
<cRouteProperties xmlns:d="http://www.kuju.com/TnT/2003/Delta" d:version="1.0" d:id="790629576">
	<ID>
		<cGUID>
			<UUID>
				<e d:type="sUInt64">5692612645116418069</e>
				<e d:type="sUInt64">214171459967267460</e>
			</UUID>
			<DevString d:type="cDeltaString">3c0f9815-390a-4f00-8432-60e0cee3f802</DevString>
		</cGUID>
	</ID>
	<DisplayName>
		<Localisation-cUserLocalisedString>
			<English d:type="cDeltaString">CTA</English>
			<French d:type="cDeltaString"></French>
			<Italian d:type="cDeltaString"></Italian>
			<German d:type="cDeltaString"></German>
			<Spanish d:type="cDeltaString"></Spanish>
			<Dutch d:type="cDeltaString"></Dutch>
			<Polish d:type="cDeltaString"></Polish>
			<Russian d:type="cDeltaString"></Russian>
			<Other/>
			<Key d:type="cDeltaString">f07c58be-6656-4f8c-86b8-4bb201d898db</Key>
		</Localisation-cUserLocalisedString>
	</DisplayName>
	<InfrastructureModified d:type="bool">1</InfrastructureModified>
	<BlueprintID>
		<iBlueprintLibrary-cAbsoluteBlueprintID>
			<BlueprintSetID>
				<iBlueprintLibrary-cBlueprintSetID>
					<Provider d:type="cDeltaString">RSC</Provider>
					<Product d:type="cDeltaString">NewYorkNewHaven</Product>
				</iBlueprintLibrary-cBlueprintSetID>
			</BlueprintSetID>
			<BlueprintID d:type="cDeltaString">TemplateRoutes\NewYorkNewHaven.xml</BlueprintID>
		</iBlueprintLibrary-cAbsoluteBlueprintID>
	</BlueprintID>
	<Skies>
		<cRouteBlueprint-sSkies>
			<SpringSkyBlueprint>
				<iBlueprintLibrary-cAbsoluteBlueprintID>
					<BlueprintSetID>
						<iBlueprintLibrary-cBlueprintSetID>
							<Provider d:type="cDeltaString">RSC</Provider>
							<Product d:type="cDeltaString">NewYorkNewHaven</Product>
						</iBlueprintLibrary-cBlueprintSetID>
					</BlueprintSetID>
					<BlueprintID d:type="cDeltaString">TimeOfDay\Spring.xml</BlueprintID>
				</iBlueprintLibrary-cAbsoluteBlueprintID>
			</SpringSkyBlueprint>
			<SummerSkyBlueprint>
				<iBlueprintLibrary-cAbsoluteBlueprintID>
					<BlueprintSetID>
						<iBlueprintLibrary-cBlueprintSetID>
							<Provider d:type="cDeltaString">RSC</Provider>
							<Product d:type="cDeltaString">NewYorkNewHaven</Product>
						</iBlueprintLibrary-cBlueprintSetID>
					</BlueprintSetID>
					<BlueprintID d:type="cDeltaString">TimeOfDay\Summer.xml</BlueprintID>
				</iBlueprintLibrary-cAbsoluteBlueprintID>
			</SummerSkyBlueprint>
			<AutumnSkyBlueprint>
				<iBlueprintLibrary-cAbsoluteBlueprintID>
					<BlueprintSetID>
						<iBlueprintLibrary-cBlueprintSetID>
							<Provider d:type="cDeltaString">RSC</Provider>
							<Product d:type="cDeltaString">NewYorkNewHaven</Product>
						</iBlueprintLibrary-cBlueprintSetID>
					</BlueprintSetID>
					<BlueprintID d:type="cDeltaString">TimeOfDay\Autumn.xml</BlueprintID>
				</iBlueprintLibrary-cAbsoluteBlueprintID>
			</AutumnSkyBlueprint>
			<WinterSkyBlueprint>
				<iBlueprintLibrary-cAbsoluteBlueprintID>
					<BlueprintSetID>
						<iBlueprintLibrary-cBlueprintSetID>
							<Provider d:type="cDeltaString">RSC</Provider>
							<Product d:type="cDeltaString">NewYorkNewHaven</Product>
						</iBlueprintLibrary-cBlueprintSetID>
					</BlueprintSetID>
					<BlueprintID d:type="cDeltaString">TimeOfDay\Winter.xml</BlueprintID>
				</iBlueprintLibrary-cAbsoluteBlueprintID>
			</WinterSkyBlueprint>
		</cRouteBlueprint-sSkies>
	</Skies>
	<WeatherBlueprint>
		<iBlueprintLibrary-cAbsoluteBlueprintID>
			<BlueprintSetID>
				<iBlueprintLibrary-cBlueprintSetID>
					<Provider d:type="cDeltaString">RSC</Provider>
					<Product d:type="cDeltaString">NewYorkNewHaven</Product>
				</iBlueprintLibrary-cBlueprintSetID>
			</BlueprintSetID>
			<BlueprintID d:type="cDeltaString">Weather\Cloudy.xml</BlueprintID>
		</iBlueprintLibrary-cAbsoluteBlueprintID>
	</WeatherBlueprint>
	<TerrainBlueprint>
		<iBlueprintLibrary-cAbsoluteBlueprintID>
			<BlueprintSetID>
				<iBlueprintLibrary-cBlueprintSetID>
					<Provider d:type="cDeltaString">RSC</Provider>
					<Product d:type="cDeltaString">NewYorkNewHaven</Product>
				</iBlueprintLibrary-cBlueprintSetID>
			</BlueprintSetID>
			<BlueprintID d:type="cDeltaString">Environment\Terrain\Terrain.xml</BlueprintID>
		</iBlueprintLibrary-cAbsoluteBlueprintID>
	</TerrainBlueprint>
	<MapBlueprint>
		<iBlueprintLibrary-cAbsoluteBlueprintID>
			<BlueprintSetID>
				<iBlueprintLibrary-cBlueprintSetID>
					<Provider d:type="cDeltaString">RSC</Provider>
					<Product d:type="cDeltaString">NewYorkNewHaven</Product>
				</iBlueprintLibrary-cBlueprintSetID>
			</BlueprintSetID>
			<BlueprintID d:type="cDeltaString">System\Map\map.xml</BlueprintID>
		</iBlueprintLibrary-cAbsoluteBlueprintID>
	</MapBlueprint>
	<LockCounter d:type="sUInt32">1</LockCounter>
	<Locked d:type="bool">0</Locked>
	<MapProjection>
		<cMapProjectionOwner d:id="790482904">
			<MapProjection>
				<cUTMMapProjection d:id="792747112">
					<Origin>
						<sGeoPosition>
							<Lat d:type="sFloat64" d:alt_encoding="F5DBD78173F64440" d:precision="string">41.9254</Lat>
							<Long d:type="sFloat64" d:alt_encoding="0BB5A679C7E955C0" d:precision="string">-87.6528</Long>
						</sGeoPosition>
					</Origin>
					<MapOffset>
						<sMapCoords>
							<Easting d:type="sFloat64" d:alt_encoding="CDCCCCCC3C6EEAC0" d:precision="string">-54129.9</Easting>
							<Northing d:type="sFloat64" d:alt_encoding="00000000E9B45141" d:precision="string">4.6417e+006</Northing>
						</sMapCoords>
					</MapOffset>
					<ZoneNumber d:type="sInt32">16</ZoneNumber>
					<ZoneLetter d:type="cDeltaString">T</ZoneLetter>
				</cUTMMapProjection>
			</MapProjection>
		</cMapProjectionOwner>
	</MapProjection>
	<RBlueprintSetPreLoad>
		<iBlueprintLibrary-cBlueprintSetID d:id="1172870928">
			<Provider d:type="cDeltaString">briman0094</Provider>
			<Product d:type="cDeltaString">CTA</Product>
		</iBlueprintLibrary-cBlueprintSetID>
		<iBlueprintLibrary-cBlueprintSetID d:id="1172870936">
			<Provider d:type="cDeltaString">RSC</Provider>
			<Product d:type="cDeltaString">NewYorkNewHaven</Product>
		</iBlueprintLibrary-cBlueprintSetID>
		<iBlueprintLibrary-cBlueprintSetID d:id="1172870944">
			<Provider d:type="cDeltaString">Barnez</Provider>
			<Product d:type="cDeltaString">BNSFChicago</Product>
		</iBlueprintLibrary-cBlueprintSetID>
	</RBlueprintSetPreLoad>
	<AuthoredLanguage d:type="cDeltaString">en</AuthoredLanguage>
	<Version d:type="sFloat32" d:alt_encoding="000000000000F03F" d:precision="string">1</Version>
	<TimeZone d:type="sFloat32" d:alt_encoding="0000000000000000" d:precision="string">0</TimeZone>
	<SummerTime d:type="sFloat32" d:alt_encoding="000000000020AC40" d:precision="string">3600</SummerTime>
	<HasTimeZoneSet d:type="bool">0</HasTimeZoneSet>
	<HasSpeedsigns d:type="bool">1</HasSpeedsigns>
	<WorkshopId d:type="sUInt64">0</WorkshopId>
	<WorkshopBy d:type="sUInt64">0</WorkshopBy>
	<WorkshopTags d:type="cDeltaString"></WorkshopTags>
</cRouteProperties>
